mimesis/__init__.py
mimesis/compat.py
mimesis/constants.py
mimesis/entrypoints.py
mimesis/enums.py
mimesis/exceptions.py
mimesis/keys.py
mimesis/locales.py
mimesis/py.typed
mimesis/random.py
mimesis/schema.py
mimesis/shortcuts.py
mimesis/types.py
mimesis/datasets/__init__.py
mimesis/datasets/ar/address.json
mimesis/datasets/ar/business.json
mimesis/datasets/ar/datetime.json
mimesis/datasets/ar/finance.json
mimesis/datasets/ar/food.json
mimesis/datasets/ar/person.json
mimesis/datasets/ar/text.json
mimesis/datasets/ar-ae/address.json
mimesis/datasets/ar-ae/business.json
mimesis/datasets/ar-ae/datetime.json
mimesis/datasets/ar-ae/finance.json
mimesis/datasets/ar-ae/food.json
mimesis/datasets/ar-ae/person.json
mimesis/datasets/ar-ae/text.json
mimesis/datasets/ar-dz/address.json
mimesis/datasets/ar-dz/business.json
mimesis/datasets/ar-dz/datetime.json
mimesis/datasets/ar-dz/finance.json
mimesis/datasets/ar-dz/food.json
mimesis/datasets/ar-dz/person.json
mimesis/datasets/ar-dz/text.json
mimesis/datasets/ar-eg/address.json
mimesis/datasets/ar-eg/business.json
mimesis/datasets/ar-eg/datetime.json
mimesis/datasets/ar-eg/finance.json
mimesis/datasets/ar-eg/food.json
mimesis/datasets/ar-eg/person.json
mimesis/datasets/ar-eg/text.json
mimesis/datasets/ar-jo/address.json
mimesis/datasets/ar-jo/business.json
mimesis/datasets/ar-jo/datetime.json
mimesis/datasets/ar-jo/finance.json
mimesis/datasets/ar-jo/food.json
mimesis/datasets/ar-jo/person.json
mimesis/datasets/ar-jo/text.json
mimesis/datasets/ar-kw/address.json
mimesis/datasets/ar-kw/business.json
mimesis/datasets/ar-kw/datetime.json
mimesis/datasets/ar-kw/finance.json
mimesis/datasets/ar-kw/food.json
mimesis/datasets/ar-kw/person.json
mimesis/datasets/ar-kw/text.json
mimesis/datasets/ar-ma/address.json
mimesis/datasets/ar-ma/business.json
mimesis/datasets/ar-ma/datetime.json
mimesis/datasets/ar-ma/finance.json
mimesis/datasets/ar-ma/food.json
mimesis/datasets/ar-ma/person.json
mimesis/datasets/ar-ma/text.json
mimesis-19.0.0.dist-info/METADATA
mimesis-19.0.0.dist-info/WHEEL
mimesis-19.0.0.dist-info/entry_points.txt
mimesis-19.0.0.dist-info/licenses/LICENSE
mimesis-19.0.0.dist-info/RECORD
