Metadata-Version: 2.4
Name: mimesis
Version: 19.0.0
Summary: Mimesis: Fake Data Generator.
Project-URL: Homepage, https://github.com/lk-geimfari/mimesis
Project-URL: Repository, https://github.com/lk-geimfari/mimesis
Project-URL: Documentation, https://mimesis.name
Author-email: Isaak Uchakaev <hey@isaak.dev>
License-Expression: MIT
License-File: LICENSE
Keywords: data,database,dataframe,datascince,dummy,factory,factory_boy,fake,faker,fixtures,generate,mimesis,mock,pandas,polars,populate,pytest,schema,testing
Classifier: Development Status :: 5 - Production/Stable
Classifier: Intended Audience :: Developers
Classifier: License :: OSI Approved :: MIT License
Classifier: Operating System :: OS Independent
Classifier: Programming Language :: Python
Classifier: Programming Language :: Python :: 3
Classifier: Programming Language :: Python :: 3 :: Only
Classifier: Programming Language :: Python :: 3.10
Classifier: Programming Language :: Python :: 3.11
Classifier: Programming Language :: Python :: 3.12
Classifier: Programming Language :: Python :: 3.13
Classifier: Programming Language :: Python :: 3.14
Classifier: Programming Language :: Python :: Implementation :: CPython
Classifier: Programming Language :: Python :: Implementation :: PyPy
Classifier: Topic :: Software Development
Classifier: Topic :: Software Development :: Testing
Classifier: Topic :: Utilities
Requires-Python: ~=3.10
Provides-Extra: factory
Requires-Dist: factory-boy<4,>=3.3.0; extra == 'factory'
